{
  "cardCount": 9,
  "cards": [
    {
      "artist": null,
      "availableVariants": [],
      "canonicalBaseId": "pokemon|en|pkmsm|DAR|darkness_energy",
      "collectorNumber": "DAR",
      "displayName": "Darkness Energy",
      "externalIds": {
        "pokemonTcgApiId": null,
        "pricechartingId": null,
        "tcgdexCardId": null,
        "tcgplayerProductId": null
      },
      "game": "pokemon",
      "hp": null,
      "illustrator": null,
      "imageCached": false,
      "imageLarge": "https://api.pokewallet.io/images/18ebf673c51226c954674cc5853b046b4f0115b61bf29b988ae88524ad9712a0?size=high",
      "imageSmall": "https://api.pokewallet.io/images/18ebf673c51226c954674cc5853b046b4f0115b61bf29b988ae88524ad9712a0?size=low",
      "imageSource": "pokewallet",
      "language": "en",
      "name": "Darkness Energy",
      "normalizedName": "darkness_energy",
      "originalName": "Darkness Energy (PKMSM DAR)",
      "pricingReferences": {
        "cardmarketAvailable": true,
        "pokewalletAvailable": true,
        "tcgplayerAvailable": false
      },
      "promotionMetadata": {
        "confidence": "provider_catalog_identity",
        "identityKey": "en|pkmsm|dar|darkness_energy|normal",
        "provider": "pokewallet",
        "providerCardId": "18ebf673c51226c954674cc5853b046b4f0115b61bf29b988ae88524ad9712a0",
        "providerFile": "public/v1/provider-catalog/pokewallet/cards/en/-146.json",
        "providerLanguage": "eng",
        "providerSetCode": "PKMSM",
        "providerSetId": "-146",
        "providerSetName": "PKMSM",
        "source": "pokewallet_provider_promotion",
        "variantKey": "normal"
      },
      "providerIds": {
        "pokemonTcgApi": null,
        "pokewallet": "18ebf673c51226c954674cc5853b046b4f0115b61bf29b988ae88524ad9712a0",
        "tcgdex": null
      },
      "rarity": "",
      "setId": "pkmsm",
      "setName": "PKMSM",
      "subtypes": [],
      "supertype": null,
      "supertypes": [],
      "types": []
    },
    {
      "artist": null,
      "availableVariants": [],
      "canonicalBaseId": "pokemon|en|pkmsm|FAI|fairy_energy",
      "collectorNumber": "FAI",
      "displayName": "Fairy Energy",
      "externalIds": {
        "pokemonTcgApiId": null,
        "pricechartingId": null,
        "tcgdexCardId": null,
        "tcgplayerProductId": null
      },
      "game": "pokemon",
      "hp": null,
      "illustrator": null,
      "imageCached": false,
      "imageLarge": "https://api.pokewallet.io/images/a76cf671a5b7c0908a99c8e53b633c8749675cb40feaac6ab809d4e2a7fa9165?size=high",
      "imageSmall": "https://api.pokewallet.io/images/a76cf671a5b7c0908a99c8e53b633c8749675cb40feaac6ab809d4e2a7fa9165?size=low",
      "imageSource": "pokewallet",
      "language": "en",
      "name": "Fairy Energy",
      "normalizedName": "fairy_energy",
      "originalName": "Fairy Energy (PKMSM FAI)",
      "pricingReferences": {
        "cardmarketAvailable": true,
        "pokewalletAvailable": true,
        "tcgplayerAvailable": false
      },
      "promotionMetadata": {
        "confidence": "provider_catalog_identity",
        "identityKey": "en|pkmsm|fai|fairy_energy|normal",
        "provider": "pokewallet",
        "providerCardId": "a76cf671a5b7c0908a99c8e53b633c8749675cb40feaac6ab809d4e2a7fa9165",
        "providerFile": "public/v1/provider-catalog/pokewallet/cards/en/-146.json",
        "providerLanguage": "eng",
        "providerSetCode": "PKMSM",
        "providerSetId": "-146",
        "providerSetName": "PKMSM",
        "source": "pokewallet_provider_promotion",
        "variantKey": "normal"
      },
      "providerIds": {
        "pokemonTcgApi": null,
        "pokewallet": "a76cf671a5b7c0908a99c8e53b633c8749675cb40feaac6ab809d4e2a7fa9165",
        "tcgdex": null
      },
      "rarity": "",
      "setId": "pkmsm",
      "setName": "PKMSM",
      "subtypes": [],
      "supertype": null,
      "supertypes": [],
      "types": []
    },
    {
      "artist": null,
      "availableVariants": [],
      "canonicalBaseId": "pokemon|en|pkmsm|FIG|fighting_energy",
      "collectorNumber": "FIG",
      "displayName": "Fighting Energy",
      "externalIds": {
        "pokemonTcgApiId": null,
        "pricechartingId": null,
        "tcgdexCardId": null,
        "tcgplayerProductId": null
      },
      "game": "pokemon",
      "hp": null,
      "illustrator": null,
      "imageCached": false,
      "imageLarge": "https://api.pokewallet.io/images/dc3f868e7ca731b2819b3c224db07fce6e302a6335889db6c0aab6103aba5fb6?size=high",
      "imageSmall": "https://api.pokewallet.io/images/dc3f868e7ca731b2819b3c224db07fce6e302a6335889db6c0aab6103aba5fb6?size=low",
      "imageSource": "pokewallet",
      "language": "en",
      "name": "Fighting Energy",
      "normalizedName": "fighting_energy",
      "originalName": "Fighting Energy (PKMSM FIG)",
      "pricingReferences": {
        "cardmarketAvailable": true,
        "pokewalletAvailable": true,
        "tcgplayerAvailable": false
      },
      "promotionMetadata": {
        "confidence": "provider_catalog_identity",
        "identityKey": "en|pkmsm|fig|fighting_energy|normal",
        "provider": "pokewallet",
        "providerCardId": "dc3f868e7ca731b2819b3c224db07fce6e302a6335889db6c0aab6103aba5fb6",
        "providerFile": "public/v1/provider-catalog/pokewallet/cards/en/-146.json",
        "providerLanguage": "eng",
        "providerSetCode": "PKMSM",
        "providerSetId": "-146",
        "providerSetName": "PKMSM",
        "source": "pokewallet_provider_promotion",
        "variantKey": "normal"
      },
      "providerIds": {
        "pokemonTcgApi": null,
        "pokewallet": "dc3f868e7ca731b2819b3c224db07fce6e302a6335889db6c0aab6103aba5fb6",
        "tcgdex": null
      },
      "rarity": "",
      "setId": "pkmsm",
      "setName": "PKMSM",
      "subtypes": [],
      "supertype": null,
      "supertypes": [],
      "types": []
    },
    {
      "artist": null,
      "availableVariants": [],
      "canonicalBaseId": "pokemon|en|pkmsm|FIR|fire_energy",
      "collectorNumber": "FIR",
      "displayName": "Fire Energy",
      "externalIds": {
        "pokemonTcgApiId": null,
        "pricechartingId": null,
        "tcgdexCardId": null,
        "tcgplayerProductId": null
      },
      "game": "pokemon",
      "hp": null,
      "illustrator": null,
      "imageCached": false,
      "imageLarge": "https://api.pokewallet.io/images/50bd5e03abfac4ad5dd3f854e736f6b0e34003917b9f2f4da529e5a70c020b55?size=high",
      "imageSmall": "https://api.pokewallet.io/images/50bd5e03abfac4ad5dd3f854e736f6b0e34003917b9f2f4da529e5a70c020b55?size=low",
      "imageSource": "pokewallet",
      "language": "en",
      "name": "Fire Energy",
      "normalizedName": "fire_energy",
      "originalName": "Fire Energy (PKMSM FIR)",
      "pricingReferences": {
        "cardmarketAvailable": true,
        "pokewalletAvailable": true,
        "tcgplayerAvailable": false
      },
      "promotionMetadata": {
        "confidence": "provider_catalog_identity",
        "identityKey": "en|pkmsm|fir|fire_energy|normal",
        "provider": "pokewallet",
        "providerCardId": "50bd5e03abfac4ad5dd3f854e736f6b0e34003917b9f2f4da529e5a70c020b55",
        "providerFile": "public/v1/provider-catalog/pokewallet/cards/en/-146.json",
        "providerLanguage": "eng",
        "providerSetCode": "PKMSM",
        "providerSetId": "-146",
        "providerSetName": "PKMSM",
        "source": "pokewallet_provider_promotion",
        "variantKey": "normal"
      },
      "providerIds": {
        "pokemonTcgApi": null,
        "pokewallet": "50bd5e03abfac4ad5dd3f854e736f6b0e34003917b9f2f4da529e5a70c020b55",
        "tcgdex": null
      },
      "rarity": "",
      "setId": "pkmsm",
      "setName": "PKMSM",
      "subtypes": [],
      "supertype": null,
      "supertypes": [],
      "types": []
    },
    {
      "artist": null,
      "availableVariants": [],
      "canonicalBaseId": "pokemon|en|pkmsm|GRA|grass_energy",
      "collectorNumber": "GRA",
      "displayName": "Grass Energy",
      "externalIds": {
        "pokemonTcgApiId": null,
        "pricechartingId": null,
        "tcgdexCardId": null,
        "tcgplayerProductId": null
      },
      "game": "pokemon",
      "hp": null,
      "illustrator": null,
      "imageCached": false,
      "imageLarge": "https://api.pokewallet.io/images/e71b0aa8384752e532eea840ed9b38ce97f1ce44c2596ef3c41f66a9429e6573?size=high",
      "imageSmall": "https://api.pokewallet.io/images/e71b0aa8384752e532eea840ed9b38ce97f1ce44c2596ef3c41f66a9429e6573?size=low",
      "imageSource": "pokewallet",
      "language": "en",
      "name": "Grass Energy",
      "normalizedName": "grass_energy",
      "originalName": "Grass Energy (PKMSM GRA)",
      "pricingReferences": {
        "cardmarketAvailable": true,
        "pokewalletAvailable": true,
        "tcgplayerAvailable": false
      },
      "promotionMetadata": {
        "confidence": "provider_catalog_identity",
        "identityKey": "en|pkmsm|gra|grass_energy|normal",
        "provider": "pokewallet",
        "providerCardId": "e71b0aa8384752e532eea840ed9b38ce97f1ce44c2596ef3c41f66a9429e6573",
        "providerFile": "public/v1/provider-catalog/pokewallet/cards/en/-146.json",
        "providerLanguage": "eng",
        "providerSetCode": "PKMSM",
        "providerSetId": "-146",
        "providerSetName": "PKMSM",
        "source": "pokewallet_provider_promotion",
        "variantKey": "normal"
      },
      "providerIds": {
        "pokemonTcgApi": null,
        "pokewallet": "e71b0aa8384752e532eea840ed9b38ce97f1ce44c2596ef3c41f66a9429e6573",
        "tcgdex": null
      },
      "rarity": "",
      "setId": "pkmsm",
      "setName": "PKMSM",
      "subtypes": [],
      "supertype": null,
      "supertypes": [],
      "types": []
    },
    {
      "artist": null,
      "availableVariants": [],
      "canonicalBaseId": "pokemon|en|pkmsm|LIG|lightning_energy",
      "collectorNumber": "LIG",
      "displayName": "Lightning Energy",
      "externalIds": {
        "pokemonTcgApiId": null,
        "pricechartingId": null,
        "tcgdexCardId": null,
        "tcgplayerProductId": null
      },
      "game": "pokemon",
      "hp": null,
      "illustrator": null,
      "imageCached": false,
      "imageLarge": "https://api.pokewallet.io/images/ce4c2e8b0ba099cd82d780f5d1e091eb360b7298c2c21e0c658d1bf60e1d0710?size=high",
      "imageSmall": "https://api.pokewallet.io/images/ce4c2e8b0ba099cd82d780f5d1e091eb360b7298c2c21e0c658d1bf60e1d0710?size=low",
      "imageSource": "pokewallet",
      "language": "en",
      "name": "Lightning Energy",
      "normalizedName": "lightning_energy",
      "originalName": "Lightning Energy (PKMSM LIG)",
      "pricingReferences": {
        "cardmarketAvailable": true,
        "pokewalletAvailable": true,
        "tcgplayerAvailable": false
      },
      "promotionMetadata": {
        "confidence": "provider_catalog_identity",
        "identityKey": "en|pkmsm|lig|lightning_energy|normal",
        "provider": "pokewallet",
        "providerCardId": "ce4c2e8b0ba099cd82d780f5d1e091eb360b7298c2c21e0c658d1bf60e1d0710",
        "providerFile": "public/v1/provider-catalog/pokewallet/cards/en/-146.json",
        "providerLanguage": "eng",
        "providerSetCode": "PKMSM",
        "providerSetId": "-146",
        "providerSetName": "PKMSM",
        "source": "pokewallet_provider_promotion",
        "variantKey": "normal"
      },
      "providerIds": {
        "pokemonTcgApi": null,
        "pokewallet": "ce4c2e8b0ba099cd82d780f5d1e091eb360b7298c2c21e0c658d1bf60e1d0710",
        "tcgdex": null
      },
      "rarity": "",
      "setId": "pkmsm",
      "setName": "PKMSM",
      "subtypes": [],
      "supertype": null,
      "supertypes": [],
      "types": []
    },
    {
      "artist": null,
      "availableVariants": [],
      "canonicalBaseId": "pokemon|en|pkmsm|MET|metal_energy",
      "collectorNumber": "MET",
      "displayName": "Metal Energy",
      "externalIds": {
        "pokemonTcgApiId": null,
        "pricechartingId": null,
        "tcgdexCardId": null,
        "tcgplayerProductId": null
      },
      "game": "pokemon",
      "hp": null,
      "illustrator": null,
      "imageCached": false,
      "imageLarge": "https://api.pokewallet.io/images/8ad9b22b6ecb833a5ebdbeb89e7b79e8cad62f472a5d3b62fb2f009637518425?size=high",
      "imageSmall": "https://api.pokewallet.io/images/8ad9b22b6ecb833a5ebdbeb89e7b79e8cad62f472a5d3b62fb2f009637518425?size=low",
      "imageSource": "pokewallet",
      "language": "en",
      "name": "Metal Energy",
      "normalizedName": "metal_energy",
      "originalName": "Metal Energy (PKMSM MET)",
      "pricingReferences": {
        "cardmarketAvailable": true,
        "pokewalletAvailable": true,
        "tcgplayerAvailable": false
      },
      "promotionMetadata": {
        "confidence": "provider_catalog_identity",
        "identityKey": "en|pkmsm|met|metal_energy|normal",
        "provider": "pokewallet",
        "providerCardId": "8ad9b22b6ecb833a5ebdbeb89e7b79e8cad62f472a5d3b62fb2f009637518425",
        "providerFile": "public/v1/provider-catalog/pokewallet/cards/en/-146.json",
        "providerLanguage": "eng",
        "providerSetCode": "PKMSM",
        "providerSetId": "-146",
        "providerSetName": "PKMSM",
        "source": "pokewallet_provider_promotion",
        "variantKey": "normal"
      },
      "providerIds": {
        "pokemonTcgApi": null,
        "pokewallet": "8ad9b22b6ecb833a5ebdbeb89e7b79e8cad62f472a5d3b62fb2f009637518425",
        "tcgdex": null
      },
      "rarity": "",
      "setId": "pkmsm",
      "setName": "PKMSM",
      "subtypes": [],
      "supertype": null,
      "supertypes": [],
      "types": []
    },
    {
      "artist": null,
      "availableVariants": [],
      "canonicalBaseId": "pokemon|en|pkmsm|PSY|psychic_energy",
      "collectorNumber": "PSY",
      "displayName": "Psychic Energy",
      "externalIds": {
        "pokemonTcgApiId": null,
        "pricechartingId": null,
        "tcgdexCardId": null,
        "tcgplayerProductId": null
      },
      "game": "pokemon",
      "hp": null,
      "illustrator": null,
      "imageCached": false,
      "imageLarge": "https://api.pokewallet.io/images/6a78f105bd23f5c70ed13164e5971b03f63706e290d4f2da6178669460e786fc?size=high",
      "imageSmall": "https://api.pokewallet.io/images/6a78f105bd23f5c70ed13164e5971b03f63706e290d4f2da6178669460e786fc?size=low",
      "imageSource": "pokewallet",
      "language": "en",
      "name": "Psychic Energy",
      "normalizedName": "psychic_energy",
      "originalName": "Psychic Energy (PKMSM PSY)",
      "pricingReferences": {
        "cardmarketAvailable": true,
        "pokewalletAvailable": true,
        "tcgplayerAvailable": false
      },
      "promotionMetadata": {
        "confidence": "provider_catalog_identity",
        "identityKey": "en|pkmsm|psy|psychic_energy|normal",
        "provider": "pokewallet",
        "providerCardId": "6a78f105bd23f5c70ed13164e5971b03f63706e290d4f2da6178669460e786fc",
        "providerFile": "public/v1/provider-catalog/pokewallet/cards/en/-146.json",
        "providerLanguage": "eng",
        "providerSetCode": "PKMSM",
        "providerSetId": "-146",
        "providerSetName": "PKMSM",
        "source": "pokewallet_provider_promotion",
        "variantKey": "normal"
      },
      "providerIds": {
        "pokemonTcgApi": null,
        "pokewallet": "6a78f105bd23f5c70ed13164e5971b03f63706e290d4f2da6178669460e786fc",
        "tcgdex": null
      },
      "rarity": "",
      "setId": "pkmsm",
      "setName": "PKMSM",
      "subtypes": [],
      "supertype": null,
      "supertypes": [],
      "types": []
    },
    {
      "artist": null,
      "availableVariants": [],
      "canonicalBaseId": "pokemon|en|pkmsm|WAT|water_energy",
      "collectorNumber": "WAT",
      "displayName": "Water Energy",
      "externalIds": {
        "pokemonTcgApiId": null,
        "pricechartingId": null,
        "tcgdexCardId": null,
        "tcgplayerProductId": null
      },
      "game": "pokemon",
      "hp": null,
      "illustrator": null,
      "imageCached": false,
      "imageLarge": "https://api.pokewallet.io/images/25b42843cc8b3fe03f59a9d4877d3af71abd3cd26aa59c5ff94655cab5d2340c?size=high",
      "imageSmall": "https://api.pokewallet.io/images/25b42843cc8b3fe03f59a9d4877d3af71abd3cd26aa59c5ff94655cab5d2340c?size=low",
      "imageSource": "pokewallet",
      "language": "en",
      "name": "Water Energy",
      "normalizedName": "water_energy",
      "originalName": "Water Energy (PKMSM WAT)",
      "pricingReferences": {
        "cardmarketAvailable": true,
        "pokewalletAvailable": true,
        "tcgplayerAvailable": false
      },
      "promotionMetadata": {
        "confidence": "provider_catalog_identity",
        "identityKey": "en|pkmsm|wat|water_energy|normal",
        "provider": "pokewallet",
        "providerCardId": "25b42843cc8b3fe03f59a9d4877d3af71abd3cd26aa59c5ff94655cab5d2340c",
        "providerFile": "public/v1/provider-catalog/pokewallet/cards/en/-146.json",
        "providerLanguage": "eng",
        "providerSetCode": "PKMSM",
        "providerSetId": "-146",
        "providerSetName": "PKMSM",
        "source": "pokewallet_provider_promotion",
        "variantKey": "normal"
      },
      "providerIds": {
        "pokemonTcgApi": null,
        "pokewallet": "25b42843cc8b3fe03f59a9d4877d3af71abd3cd26aa59c5ff94655cab5d2340c",
        "tcgdex": null
      },
      "rarity": "",
      "setId": "pkmsm",
      "setName": "PKMSM",
      "subtypes": [],
      "supertype": null,
      "supertypes": [],
      "types": []
    }
  ],
  "catalogueStatus": "built",
  "game": "pokemon",
  "generatedAtUtc": "2026-05-23T06:00:36Z",
  "language": "en",
  "schemaVersion": "1.0.0",
  "setId": "pkmsm",
  "setName": "PKMSM",
  "source": "pokewallet"
}
