{
  "cardCount": 5,
  "cardScanRLanguage": "jp",
  "cards": [
    {
      "canonicalImageKey": null,
      "cardNumber": "001/010",
      "cardScanRImageCacheCandidateKey": "pokemon|jp|24059|001-010|tropius|normal",
      "cardScanRLanguage": "jp",
      "cleanName": "Tropius",
      "hasCardmarketFields": true,
      "hasPriceFields": true,
      "hasTcgplayerFields": true,
      "imageAvailable": null,
      "imageCacheIdentityBasis": {
        "basisConfidence": "provider_catalog_candidate",
        "collectorNumber": "001/010",
        "game": "pokemon",
        "language": "jp",
        "normalizedName": "tropius",
        "setId": "24059",
        "variant": "normal"
      },
      "imageCacheKey": "pokemon|jp|24059|001-010|tropius|normal",
      "imageCacheStrategy": "cache_once_recheck_on_failure",
      "imageEndpoint": "/images/pk_547619bef646cd85c347c09512af1c0725bac30236686cde086e68902f6977dac39c317cb232c62742f18c22a090",
      "imageEndpointHigh": "/images/pk_547619bef646cd85c347c09512af1c0725bac30236686cde086e68902f6977dac39c317cb232c62742f18c22a090?size=high",
      "imageEndpointLow": "/images/pk_547619bef646cd85c347c09512af1c0725bac30236686cde086e68902f6977dac39c317cb232c62742f18c22a090?size=low",
      "imageHighAvailable": null,
      "imageLastCheckedAtUtc": null,
      "imageLowAvailable": null,
      "name": "Tropius",
      "providerCanonicalImageKey": "pokemon|jp|24059|001-010|tropius|normal",
      "providerCardId": "pk_547619bef646cd85c347c09512af1c0725bac30236686cde086e68902f6977dac39c317cb232c62742f18c22a090",
      "providerLanguage": "jap",
      "providerSetCode": "24059",
      "providerSetId": "24059",
      "providerSetName": "Battle Starter Deck (Torterra)",
      "rarity": "",
      "rawKeys": [
        "card_info",
        "cardmarket",
        "id",
        "tcgplayer"
      ],
      "variants": []
    },
    {
      "canonicalImageKey": null,
      "cardNumber": "002/010",
      "cardScanRImageCacheCandidateKey": "pokemon|jp|24059|002-010|turtwig|normal",
      "cardScanRLanguage": "jp",
      "cleanName": "Turtwig",
      "hasCardmarketFields": true,
      "hasPriceFields": true,
      "hasTcgplayerFields": true,
      "imageAvailable": null,
      "imageCacheIdentityBasis": {
        "basisConfidence": "provider_catalog_candidate",
        "collectorNumber": "002/010",
        "game": "pokemon",
        "language": "jp",
        "normalizedName": "turtwig",
        "setId": "24059",
        "variant": "normal"
      },
      "imageCacheKey": "pokemon|jp|24059|002-010|turtwig|normal",
      "imageCacheStrategy": "cache_once_recheck_on_failure",
      "imageEndpoint": "/images/pk_26de0daf4350905c6d505bd6944aada1ca9366bd3d0e7f869b6bfa2a2ab18615aabe63a5378e673cc777ea812d1d",
      "imageEndpointHigh": "/images/pk_26de0daf4350905c6d505bd6944aada1ca9366bd3d0e7f869b6bfa2a2ab18615aabe63a5378e673cc777ea812d1d?size=high",
      "imageEndpointLow": "/images/pk_26de0daf4350905c6d505bd6944aada1ca9366bd3d0e7f869b6bfa2a2ab18615aabe63a5378e673cc777ea812d1d?size=low",
      "imageHighAvailable": null,
      "imageLastCheckedAtUtc": null,
      "imageLowAvailable": null,
      "name": "Turtwig",
      "providerCanonicalImageKey": "pokemon|jp|24059|002-010|turtwig|normal",
      "providerCardId": "pk_26de0daf4350905c6d505bd6944aada1ca9366bd3d0e7f869b6bfa2a2ab18615aabe63a5378e673cc777ea812d1d",
      "providerLanguage": "jap",
      "providerSetCode": "24059",
      "providerSetId": "24059",
      "providerSetName": "Battle Starter Deck (Torterra)",
      "rarity": "",
      "rawKeys": [
        "card_info",
        "cardmarket",
        "id",
        "tcgplayer"
      ],
      "variants": []
    },
    {
      "canonicalImageKey": null,
      "cardNumber": "003/010",
      "cardScanRImageCacheCandidateKey": "pokemon|jp|24059|003-010|grotle|normal",
      "cardScanRLanguage": "jp",
      "cleanName": "Grotle",
      "hasCardmarketFields": true,
      "hasPriceFields": true,
      "hasTcgplayerFields": true,
      "imageAvailable": null,
      "imageCacheIdentityBasis": {
        "basisConfidence": "provider_catalog_candidate",
        "collectorNumber": "003/010",
        "game": "pokemon",
        "language": "jp",
        "normalizedName": "grotle",
        "setId": "24059",
        "variant": "normal"
      },
      "imageCacheKey": "pokemon|jp|24059|003-010|grotle|normal",
      "imageCacheStrategy": "cache_once_recheck_on_failure",
      "imageEndpoint": "/images/pk_f9d77edd0f63868ae8a53d3076a0fb07af8d87a5d875e1906557f292e7452461d5d5ff84f99c632d1b1a3d201172",
      "imageEndpointHigh": "/images/pk_f9d77edd0f63868ae8a53d3076a0fb07af8d87a5d875e1906557f292e7452461d5d5ff84f99c632d1b1a3d201172?size=high",
      "imageEndpointLow": "/images/pk_f9d77edd0f63868ae8a53d3076a0fb07af8d87a5d875e1906557f292e7452461d5d5ff84f99c632d1b1a3d201172?size=low",
      "imageHighAvailable": null,
      "imageLastCheckedAtUtc": null,
      "imageLowAvailable": null,
      "name": "Grotle",
      "providerCanonicalImageKey": "pokemon|jp|24059|003-010|grotle|normal",
      "providerCardId": "pk_f9d77edd0f63868ae8a53d3076a0fb07af8d87a5d875e1906557f292e7452461d5d5ff84f99c632d1b1a3d201172",
      "providerLanguage": "jap",
      "providerSetCode": "24059",
      "providerSetId": "24059",
      "providerSetName": "Battle Starter Deck (Torterra)",
      "rarity": "",
      "rawKeys": [
        "card_info",
        "cardmarket",
        "id",
        "tcgplayer"
      ],
      "variants": []
    },
    {
      "canonicalImageKey": null,
      "cardNumber": "004/010",
      "cardScanRImageCacheCandidateKey": "pokemon|jp|24059|004-010|torterra|normal",
      "cardScanRLanguage": "jp",
      "cleanName": "Torterra",
      "hasCardmarketFields": true,
      "hasPriceFields": true,
      "hasTcgplayerFields": true,
      "imageAvailable": null,
      "imageCacheIdentityBasis": {
        "basisConfidence": "provider_catalog_candidate",
        "collectorNumber": "004/010",
        "game": "pokemon",
        "language": "jp",
        "normalizedName": "torterra",
        "setId": "24059",
        "variant": "normal"
      },
      "imageCacheKey": "pokemon|jp|24059|004-010|torterra|normal",
      "imageCacheStrategy": "cache_once_recheck_on_failure",
      "imageEndpoint": "/images/pk_00067434f2ff6aa27b5d0d73f3c646538c4a3edec50f0d7b7835f27c91a6a2a6b8d9a09dd8f1a9e958a64e961bd4",
      "imageEndpointHigh": "/images/pk_00067434f2ff6aa27b5d0d73f3c646538c4a3edec50f0d7b7835f27c91a6a2a6b8d9a09dd8f1a9e958a64e961bd4?size=high",
      "imageEndpointLow": "/images/pk_00067434f2ff6aa27b5d0d73f3c646538c4a3edec50f0d7b7835f27c91a6a2a6b8d9a09dd8f1a9e958a64e961bd4?size=low",
      "imageHighAvailable": null,
      "imageLastCheckedAtUtc": null,
      "imageLowAvailable": null,
      "name": "Torterra",
      "providerCanonicalImageKey": "pokemon|jp|24059|004-010|torterra|normal",
      "providerCardId": "pk_00067434f2ff6aa27b5d0d73f3c646538c4a3edec50f0d7b7835f27c91a6a2a6b8d9a09dd8f1a9e958a64e961bd4",
      "providerLanguage": "jap",
      "providerSetCode": "24059",
      "providerSetId": "24059",
      "providerSetName": "Battle Starter Deck (Torterra)",
      "rarity": "",
      "rawKeys": [
        "card_info",
        "cardmarket",
        "id",
        "tcgplayer"
      ],
      "variants": []
    },
    {
      "canonicalImageKey": null,
      "cardNumber": "005/010",
      "cardScanRImageCacheCandidateKey": "pokemon|jp|24059|005-010|cherubi|normal",
      "cardScanRLanguage": "jp",
      "cleanName": "Cherubi",
      "hasCardmarketFields": true,
      "hasPriceFields": true,
      "hasTcgplayerFields": true,
      "imageAvailable": null,
      "imageCacheIdentityBasis": {
        "basisConfidence": "provider_catalog_candidate",
        "collectorNumber": "005/010",
        "game": "pokemon",
        "language": "jp",
        "normalizedName": "cherubi",
        "setId": "24059",
        "variant": "normal"
      },
      "imageCacheKey": "pokemon|jp|24059|005-010|cherubi|normal",
      "imageCacheStrategy": "cache_once_recheck_on_failure",
      "imageEndpoint": "/images/pk_84c266783e7d3a31ae45ec336ac2d3840b54190718cd8aaca7c933d04ec058a9780826e50900762627b59c79ac87",
      "imageEndpointHigh": "/images/pk_84c266783e7d3a31ae45ec336ac2d3840b54190718cd8aaca7c933d04ec058a9780826e50900762627b59c79ac87?size=high",
      "imageEndpointLow": "/images/pk_84c266783e7d3a31ae45ec336ac2d3840b54190718cd8aaca7c933d04ec058a9780826e50900762627b59c79ac87?size=low",
      "imageHighAvailable": null,
      "imageLastCheckedAtUtc": null,
      "imageLowAvailable": null,
      "name": "Cherubi",
      "providerCanonicalImageKey": "pokemon|jp|24059|005-010|cherubi|normal",
      "providerCardId": "pk_84c266783e7d3a31ae45ec336ac2d3840b54190718cd8aaca7c933d04ec058a9780826e50900762627b59c79ac87",
      "providerLanguage": "jap",
      "providerSetCode": "24059",
      "providerSetId": "24059",
      "providerSetName": "Battle Starter Deck (Torterra)",
      "rarity": "",
      "rawKeys": [
        "card_info",
        "cardmarket",
        "id",
        "tcgplayer"
      ],
      "variants": []
    }
  ],
  "game": "pokemon",
  "generatedAtUtc": "2026-05-19T04:46:31Z",
  "imageReferencesOnly": true,
  "provider": "pokewallet",
  "providerLanguage": "jap",
  "providerSetCode": "B",
  "providerSetId": "24059",
  "providerSetName": "Battle Starter Deck (Torterra)",
  "schemaVersion": "1.0.0"
}
